MANIFEST.in
README.md
requirements.txt
setup.py
pytify/__init__.py
pytify/cli.py
pytify/commander.py
pytify/darwin.py
pytify/history.py
pytify/linux.py
pytify/prompt.py
pytify/pytifylib.py
pytify/song_list.py
pytify/strategy.py
pytify.egg-info/PKG-INFO
pytify.egg-info/SOURCES.txt
pytify.egg-info/dependency_links.txt
pytify.egg-info/entry_points.txt
pytify.egg-info/requires.txt
pytify.egg-info/top_level.txt
pytify/dbus/__init__.py
pytify/dbus/interface.py
pytify/dbus/metadata.py