Metadata-Version: 1.1
Name: pytify
Version: 3.6.3
Summary: Spotify remote. Search, start and navigate through songs.
Home-page: https://github.com/bjarneo/pytify
Author: Bjarne Oeverli
Author-email: bjarne.oeverli@gmail.com
License: MIT
Download-URL: https://pypi.python.org/pypi/pytify
Keywords: spotify pytify song search curses
Platform: UNKNOWN
Classifier: Intended Audience :: End Users/Desktop
Classifier: Environment :: Console :: Curses
Classifier: Operating System :: MacOS :: MacOS X
Classifier: Operating System :: POSIX
Classifier: Natural Language :: English
Classifier: Programming Language :: Python :: 3.1
Classifier: Programming Language :: Python :: 3.2
Classifier: Programming Language :: Python :: 3.3
Classifier: Programming Language :: Python :: 3.4
Classifier: Programming Language :: Python :: 3.5
Classifier: Topic :: Terminals
